rdfingest/__init__.py
rdfingest/cli_help.py
rdfingest/ingest.py
rdfingest/ingest_strategies.py
rdfingest/main.py
rdfingest/models.py
rdfingest/parse_graph.py
rdfingest/utils/semantic_chunking.py
rdfingest/yaml_loaders.py
rdfingest-0.1.2.dist-info/LICENSE
rdfingest-0.1.2.dist-info/METADATA
rdfingest-0.1.2.dist-info/WHEEL
rdfingest-0.1.2.dist-info/entry_points.txt
rdfingest-0.1.2.dist-info/RECORD
