Metadata-Version: 2.1
Name: rdfingest
Version: 0.1.2
Summary: 
Author: Lukas Plank
Author-email: lupl@tuta.io
Requires-Python: >=3.11,<4.0
Classifier: Programming Language :: Python :: 3
Classifier: Programming Language :: Python :: 3.11
Requires-Dist: lodkit (>=0.1.13,<0.2.0)
Requires-Dist: loguru (>=0.7.2,<0.8.0)
Requires-Dist: more-itertools (>=10.2.0,<11.0.0)
Requires-Dist: pydantic (>=2.6.4,<3.0.0)
Requires-Dist: pyyaml (>=6.0.1,<7.0.0)
Requires-Dist: rdflib (>=7.0.0,<8.0.0)
Requires-Dist: requests (>=2.31.0,<3.0.0)
Requires-Dist: sparqlwrapper (>=2.0.0,<3.0.0)
Requires-Dist: typer[all] (>=0.9.0,<0.10.0)
